devstudio_mcp/__init__.py
devstudio_mcp/config.py
devstudio_mcp/registry.py
devstudio_mcp/server.py
devstudio_mcp/resources/__init__.py
devstudio_mcp/resources/media_manager.py
devstudio_mcp/tools/__init__.py
devstudio_mcp/tools/generation.py
devstudio_mcp/tools/processing.py
devstudio_mcp/tools/recording.py
devstudio_mcp/utils/__init__.py
devstudio_mcp/utils/exceptions.py
devstudio_mcp/utils/logger.py
devstudio_mcp-1.0.0.dist-info/METADATA
devstudio_mcp-1.0.0.dist-info/WHEEL
devstudio_mcp-1.0.0.dist-info/entry_points.txt
devstudio_mcp-1.0.0.dist-info/licenses/LICENSE
devstudio_mcp-1.0.0.dist-info/licenses/LICENSE-COMMERCIAL.txt
devstudio_mcp-1.0.0.dist-info/RECORD
