Metadata-Version: 2.4
Name: devstudio-mcp
Version: 1.0.0
Summary: Production-grade MCP server for screen recording, audio capture, and demo automation
Author-email: Nihit Gupta <nihitgupta.ng@outlook.com>
License-Expression: AGPL-3.0-or-later
License-File: LICENSE
License-File: LICENSE-COMMERCIAL.txt
Keywords: agpl,demo-automation,mcp,recording,screen-capture,video-recording
Classifier: Development Status :: 5 - Production/Stable
Classifier: Intended Audience :: Developers
Classifier: Programming Language :: Python :: 3.11
Classifier: Programming Language :: Python :: 3.12
Classifier: Topic :: Multimedia :: Video :: Capture
Classifier: Topic :: Software Development :: Libraries :: Python Modules
Requires-Python: >=3.11
Requires-Dist: aiofiles>=23.2.1
Requires-Dist: av>=13.0.0
Requires-Dist: fastapi>=0.104.1
Requires-Dist: fastmcp>=1.0.0
Requires-Dist: mss>=9.0.0
Requires-Dist: numpy>=1.24.0
Requires-Dist: opencv-python-headless>=4.8.1
Requires-Dist: pillow>=10.1.0
Requires-Dist: psutil>=5.9.6
Requires-Dist: pyautogui>=0.9.54
Requires-Dist: pydantic-settings>=2.1.0
Requires-Dist: pydantic>=2.5.0
Requires-Dist: python-multipart>=0.0.6
Requires-Dist: rich>=13.7.0
Requires-Dist: screeninfo>=0.8.1
Requires-Dist: sounddevice>=0.4.6
Requires-Dist: soundfile>=0.12.1
Requires-Dist: structlog>=23.2.0
Requires-Dist: uvicorn[standard]>=0.24.0
Provides-Extra: dev
Requires-Dist: bandit>=1.7.5; extra == 'dev'
Requires-Dist: black>=23.11.0; extra == 'dev'
Requires-Dist: flake8>=6.1.0; extra == 'dev'
Requires-Dist: isort>=5.12.0; extra == 'dev'
Requires-Dist: mypy>=1.7.1; extra == 'dev'
Requires-Dist: pre-commit>=3.5.0; extra == 'dev'
Requires-Dist: pytest-asyncio>=0.21.1; extra == 'dev'
Requires-Dist: pytest-cov>=4.1.0; extra == 'dev'
Requires-Dist: pytest>=7.4.3; extra == 'dev'
Requires-Dist: safety>=2.3.0; extra == 'dev'
